{
  "os":  "Linux-6.12.80-ql-generic-14-8-x86_64-with-glibc2.39",
  "python":  "CPython 3.10.20",
  "startedAt":  "2026-05-17T16:40:28.661579Z",
  "args":  [
    "--node-ip-address=192.168.62.145",
    "--node-manager-port=44339",
    "--object-store-name=/tmp/slurm-zhengqing.gao-75271/ray/session_2026-05-17_20-38-38_966221_2897523/sockets/plasma_store",
    "--raylet-name=/tmp/slurm-zhengqing.gao-75271/ray/session_2026-05-17_20-38-38_966221_2897523/sockets/raylet",
    "--redis-address=None",
    "--metrics-agent-port=0",
    "--logging-rotate-bytes=536870912",
    "--logging-rotate-backup-count=5",
    "--runtime-env-agent-port=0",
    "--gcs-address=192.168.62.145:34817",
    "--session-name=session_2026-05-17_20-38-38_966221_2897523",
    "--temp-dir=/tmp/slurm-zhengqing.gao-75271/ray",
    "--webui=127.0.0.1:8265",
    "--cluster-id=e1f0ad22e74cccda65264e89dae01bcb4c6e1d05937fec9d4033e397",
    "--worker-id=77ab768dc2888b9c5695964eb67162f1a3958b76c62133babeecb216",
    "--worker-launch-time-ms=1779035934607",
    "--node-id=4ee18cd95f83ac0d44919037a3ef7664ed62d51437554b093eeb148f",
    "--runtime-env-hash=-1580796864"
  ],
  "program":  "/nfs-stor/zhengqing.gao/yuhao.wu/lzc/conda_envs/lzc-L2PEFT/lib/python3.10/site-packages/ray/_private/workers/default_worker.py",
  "git":  {
    "remote":  "git@github-zhicheng:ZhichengLiao/L2PEFT.git",
    "commit":  "4f95bc082be23640ca49a811dbedca7370d107dc"
  },
  "email":  "zl334000@gmail.com",
  "root":  "/nfs-stor/zhengqing.gao/yuhao.wu/lzc/L2PEFT",
  "host":  "gpu-45",
  "executable":  "/nfs-stor/zhengqing.gao/yuhao.wu/lzc/conda_envs/lzc-L2PEFT/bin/python3",
  "cpu_count":  128,
  "cpu_count_logical":  256,
  "gpu":  "NVIDIA A100-SXM4-40GB",
  "gpu_count":  4,
  "disk":  {
    "/":  {
      "total":  "1073741824",
      "used":  "11902976"
    }
  },
  "memory":  {
    "total":  "540811169792"
  },
  "gpu_nvidia":  [
    {
      "name":  "NVIDIA A100-SXM4-40GB",
      "memoryTotal":  "42949672960",
      "cudaCores":  6912,
      "architecture":  "Ampere",
      "uuid":  "GPU-f693f2b6-0a4b-c8e8-ab5a-077bf8312770"
    },
    {
      "name":  "NVIDIA A100-SXM4-40GB",
      "memoryTotal":  "42949672960",
      "cudaCores":  6912,
      "architecture":  "Ampere",
      "uuid":  "GPU-a100cfb5-e30f-ef71-917f-9b6c28181ab9"
    },
    {
      "name":  "NVIDIA A100-SXM4-40GB",
      "memoryTotal":  "42949672960",
      "cudaCores":  6912,
      "architecture":  "Ampere",
      "uuid":  "GPU-46e6c6d0-5811-b70e-df21-2493c28ba82b"
    },
    {
      "name":  "NVIDIA A100-SXM4-40GB",
      "memoryTotal":  "42949672960",
      "cudaCores":  6912,
      "architecture":  "Ampere",
      "uuid":  "GPU-c071f7ec-3a64-6082-41de-539eefa92f20"
    }
  ],
  "cudaVersion":  "12.8",
  "slurm":  {
    "cluster_name":  "mbz-ciai",
    "conf":  "/etc/qlustar/common/slurm-llnl/slurm.conf",
    "cpu_bind":  "quiet,mask_cpu:0xFFFFFFFFFFFFFFFFFFFFFFFFFFFFFFFFFFFFFFFFFFFFFFFFFFFFFFFFFFFFFFFF",
    "cpu_bind_list":  "0xFFFFFFFFFFFFFFFFFFFFFFFFFFFFFFFFFFFFFFFFFFFFFFFFFFFFFFFFFFFFFFFF",
    "cpu_bind_type":  "mask_cpu:",
    "cpu_bind_verbose":  "quiet",
    "cpus_on_node":  "256",
    "cpus_per_task":  "256",
    "distribution":  "block",
    "gpus_on_node":  "4",
    "gtids":  "0",
    "job_account":  "cscc-users",
    "job_cpus_per_node":  "256",
    "job_end_time":  "1779046339",
    "job_gid":  "2002",
    "job_id":  "75271",
    "job_name":  "bash",
    "job_nodelist":  "gpu-45",
    "job_num_nodes":  "1",
    "job_partition":  "long",
    "job_qos":  "gpu-debug-qos",
    "job_start_time":  "1779035539",
    "job_uid":  "2062",
    "job_user":  "zhengqing.gao",
    "jobid":  "75271",
    "launch_node_ipaddr":  "192.168.62.241",
    "localid":  "0",
    "mem_per_node":  "262144",
    "mpi_type":  "pmix",
    "nnodes":  "1",
    "nodeid":  "0",
    "nodelist":  "gpu-45",
    "nprocs":  "1",
    "ntasks":  "1",
    "oom_kill_step":  "0",
    "pmix_mapping_serv":  "(vector,(0,1,1))",
    "pmixp_abort_agent_port":  "40993",
    "prio_process":  "0",
    "procid":  "0",
    "pty_port":  "45973",
    "pty_win_col":  "219",
    "pty_win_row":  "20",
    "script_context":  "prolog_task",
    "srun_comm_host":  "192.168.62.241",
    "srun_comm_port":  "46709",
    "step_gpus":  "0,1,2,3",
    "step_id":  "0",
    "step_launcher_port":  "46709",
    "step_nodelist":  "gpu-45",
    "step_num_nodes":  "1",
    "step_num_tasks":  "1",
    "step_tasks_per_node":  "1",
    "stepid":  "0",
    "submit_dir":  "/nfs-stor/zhengqing.gao/yuhao.wu/lzc",
    "submit_host":  "ciai-login-1",
    "task_pid":  "2892470",
    "tasks_per_node":  "1",
    "topology_addr":  "gpu-45",
    "topology_addr_pattern":  "node",
    "tres_per_task":  "cpu=256",
    "umask":  "0022"
  },
  "writerId":  "xbc6ps95uh7epdsr3dq9t94uxqg3xken"
}